pytempmail/__init__.py
temporary_mail-1.6.dist-info/METADATA
temporary_mail-1.6.dist-info/WHEEL
temporary_mail-1.6.dist-info/top_level.txt
temporary_mail-1.6.dist-info/RECORD
