Metadata-Version: 2.1
Name: temporary-mail
Version: 1.6
Summary: A Temp Mail library for python
Author: S M Shahriar Zarir
Author-email: <shahriarzariradvance@gmail.com>
Keywords: python,mail,tempmail
Classifier: Development Status :: 1 - Planning
Classifier: Intended Audience :: Developers
Classifier: Programming Language :: Python :: 3
Classifier: Operating System :: Unix
Classifier: Operating System :: MacOS :: MacOS X
Classifier: Operating System :: Microsoft :: Windows
Requires-Dist: requests
